MANIFEST.in
README.rst
setup.py
docs/HISTORY.txt
docs/LICENSE.GPL
docs/LICENSE.txt
errbit/__init__.py
errbit/client.py
errbit/configure.zcml
errbit/httpclients.py
errbit/request.py
errbit/testing.py
errbit/utils.py
errbit/xmlgenerator.py
errbit.egg-info/PKG-INFO
errbit.egg-info/SOURCES.txt
errbit.egg-info/dependency_links.txt
errbit.egg-info/entry_points.txt
errbit.egg-info/not-zip-safe
errbit.egg-info/requires.txt
errbit.egg-info/top_level.txt
errbit/ploneintegration/__init__.py
errbit/ploneintegration/cleanup.py
errbit/ploneintegration/configure.zcml
errbit/ploneintegration/loghandler.py
errbit/ploneintegration/views.py
errbit/ploneintegration/Extensions/install.py
errbit/ploneintegration/profiles/default/jsregistry.xml
errbit/ploneintegration/profiles/default/metadata.xml
errbit/ploneintegration/profiles/uninstall/jsregistry.xml
errbit/ploneintegration/resources/airbrake-shim.js
errbit/tests/__init__.py
errbit/tests/test_client.py
errbit/tests/test_filter.py
errbit/tests/test_plone_cleanup.py
errbit/tests/test_plone_javascript.py
errbit/tests/test_request.py
errbit/tests/test_uninstall.py
errbit/tests/test_utils.py
errbit/tests/test_xmlgenerator.py
errbit/tests/utils.py
errbit/tests/assets/airbrake_2_3.xsd
errbit/tests/assets/errbit_ignore.json