Metadata-Version: 1.1
Name: errbit
Version: 1.4.0
Summary: An errbit client for python
Home-page: https://github.com/4teamwork/errbit-python
Author: 4teamwork AG
Author-email: mailto:info@4teamwork.ch
License: GPL2
Keywords: errbit client python
Platform: UNKNOWN
Classifier: Intended Audience :: Developers
Classifier: Topic :: Software Development :: Libraries :: Python Modules
